README.md
setup.cfg
setup.py
keras_segmentation/__init__.py
keras_segmentation/__main__.py
keras_segmentation/cli_interface.py
keras_segmentation/metrics.py
keras_segmentation/predict.py
keras_segmentation/pretrained.py
keras_segmentation/train.py
keras_segmentation.egg-info/PKG-INFO
keras_segmentation.egg-info/SOURCES.txt
keras_segmentation.egg-info/dependency_links.txt
keras_segmentation.egg-info/entry_points.txt
keras_segmentation.egg-info/requires.txt
keras_segmentation.egg-info/top_level.txt
keras_segmentation/data_utils/__init__.py
keras_segmentation/data_utils/augmentation.py
keras_segmentation/data_utils/data_loader.py
keras_segmentation/data_utils/visualize_dataset.py
keras_segmentation/models/__init__.py
keras_segmentation/models/_pspnet_2.py
keras_segmentation/models/all_models.py
keras_segmentation/models/basic_models.py
keras_segmentation/models/config.py
keras_segmentation/models/fcn.py
keras_segmentation/models/mobilenet.py
keras_segmentation/models/model.py
keras_segmentation/models/model_utils.py
keras_segmentation/models/pspnet.py
keras_segmentation/models/resnet50.py
keras_segmentation/models/segnet.py
keras_segmentation/models/unet.py
keras_segmentation/models/vgg16.py
test/__init__.py
test/test_models.py